mutation_core-0.6.0.dist-info/licenses/LICENSE
src/__init__.py
src/analyze.py
src/cov.py
src/gen_mutations.py
src/get_changes.py
src/mutation_core.py
src/operators.py
src/report.py
tests/__init__.py
tests/test_analyze.py
tests/test_cov.py
mutation_core-0.6.0.dist-info/METADATA
mutation_core-0.6.0.dist-info/WHEEL
mutation_core-0.6.0.dist-info/entry_points.txt
mutation_core-0.6.0.dist-info/top_level.txt
mutation_core-0.6.0.dist-info/RECORD
