Metadata-Version: 2.4
Name: mutation-core
Version: 0.6.0
Summary: Mutation testing tool for Bitcoin Core
Author: Bruno Garcia
Author-email: brunoely.gc@gmail.com
Requires-Python: >=3.8
License-File: LICENSE
Dynamic: author
Dynamic: author-email
Dynamic: description
Dynamic: description-content-type
Dynamic: license-file
Dynamic: requires-python
Dynamic: summary
